upnp_forwarder/__init__.py
upnp_forwarder/core.py
upnp_forwarder-0.1.1.dist-info/METADATA
upnp_forwarder-0.1.1.dist-info/WHEEL
upnp_forwarder-0.1.1.dist-info/top_level.txt
upnp_forwarder-0.1.1.dist-info/RECORD
