Metadata-Version: 2.1
Name: upnp_forwarder
Version: 0.1.1
Summary: A Python package for UPnP port forwarding
Home-page: https://github.com/yourusername/upnp_forwarder
Author: Your Name
Classifier: Programming Language :: Python :: 3
Classifier: License :: OSI Approved :: MIT License
Classifier: Operating System :: OS Independent
Requires-Python: >=3.6
Requires-Dist: miniupnpc
